jaxsnn/__init__.py
jaxsnn/base/__init__.py
jaxsnn/base/compose.py
jaxsnn/base/params.py
jaxsnn/base/root_solving.py
jaxsnn/base/types.py
jaxsnn/base/dataset/__init__.py
jaxsnn/base/dataset/circle.py
jaxsnn/base/dataset/constant.py
jaxsnn/base/dataset/dataloader.py
jaxsnn/base/dataset/linear.py
jaxsnn/base/dataset/yinyang.py
jaxsnn/discrete/__init__.py
jaxsnn/discrete/decode.py
jaxsnn/discrete/encode.py
jaxsnn/discrete/leaky_integrate.py
jaxsnn/discrete/leaky_integrate_and_fire.py
jaxsnn/discrete/loss.py
jaxsnn/discrete/threshold.py
jaxsnn/discrete/dataset/circle.py
jaxsnn/discrete/dataset/linear.py
jaxsnn/discrete/dataset/yinyang.py
jaxsnn/event/__init__.py
jaxsnn/event/adjoint_lif.py
jaxsnn/event/construct.py
jaxsnn/event/custom_lax.py
jaxsnn/event/encode.py
jaxsnn/event/flow.py
jaxsnn/event/functional.py
jaxsnn/event/loss.py
jaxsnn/event/training.py
jaxsnn/event/transition.py
jaxsnn/event/types.py
jaxsnn/event/utils.py
jaxsnn/event/hardware/__init__.py
jaxsnn/event/hardware/experiment.py
jaxsnn/event/hardware/input_neuron.py
jaxsnn/event/hardware/module.py
jaxsnn/event/hardware/neuron.py
jaxsnn/event/hardware/synapse.py
jaxsnn/event/hardware/utils.py
jaxsnn/event/hardware/calib/__init__.py
jaxsnn/event/modules/__init__.py
jaxsnn/event/modules/leaky_integrate.py
jaxsnn/event/modules/leaky_integrate_and_fire.py
jaxsnn/event/root/__init__.py
jaxsnn/event/root/custom_root_newton.py
jaxsnn/event/root/custom_root_ttfs.py
jaxsnn/event/root/newton.py
jaxsnn/event/root/next_finder.py
jaxsnn/event/root/ttfs.py
jaxsnn/examples/plot.py
jaxsnn/examples/discrete/yinyang.py
jaxsnn/examples/event/__init__.py
jaxsnn/examples/event/yinyang_analytical.py
jaxsnn/examples/event/yinyang_event_prop.py
jaxsnn/examples/event/hardware/yinyang.py
jaxsnn/examples/event/hardware/yinyang_mock.py
jaxsnn/examples/event/hardware/calibration/madc.py
jaxsnn/examples/event/hardware/calibration/spike_times.py
jaxsnn-0.2.0.dist-info/licenses/LICENSE
jaxsnn-0.2.0.dist-info/METADATA
jaxsnn-0.2.0.dist-info/WHEEL
jaxsnn-0.2.0.dist-info/top_level.txt
jaxsnn-0.2.0.dist-info/RECORD
