Metadata-Version: 2.4
Name: jaxsnn
Version: 0.2.0
Summary: jaxsnn is an event-based approach to machine-learning-inspired training and simulation of SNNs, including support for neuromorphic backends (BrainScaleS-2).
Author-email: "Electronic Vision(s)" <visions-dev@kip.uni-heidelberg.de>
Project-URL: Homepage, https://github.com/electronicvisions/jaxsnn
Project-URL: Bug Tracker, https://github.com/electronicvisions/jaxsnn/issues
Classifier: Programming Language :: Python :: 3
Classifier: Operating System :: OS Independent
Requires-Python: >=3.8
License-File: LICENSE
Requires-Dist: jax==0.4.13; python_version == "3.8"
Requires-Dist: jaxlib==0.4.13; python_version == "3.8"
Requires-Dist: jax<=0.4.23,>=0.4.13; python_version > "3.8"
Requires-Dist: jaxlib<=0.4.23,>=0.4.13; python_version > "3.8"
Requires-Dist: scipy<1.13; python_version > "3.8"
Requires-Dist: optax>=0.1.4
Requires-Dist: tree-math>0.1.0
Requires-Dist: matplotlib
Dynamic: license-file
